mdock/__init__.py
mdock/mdock.py
mdock-0.0.2.dist-info/METADATA
mdock-0.0.2.dist-info/WHEEL
mdock-0.0.2.dist-info/top_level.txt
mdock-0.0.2.dist-info/RECORD
